[
  {
    "id": "daymet4",
    "step": "pull",
    "error": "Error in open.connection(x, \"rb\"): cannot open the connection\n"
  },
  {
    "id": "daymet4",
    "step": "tidy",
    "error": "Error in UseMethod(\"nc_vars\"): no applicable method for 'nc_vars' applied to an object of class \"NULL\"\n"
  },
  {
    "id": "ldas",
    "step": "pull",
    "error": "Error in h(simpleError(msg, call)): error in evaluating the argument 'x' in selecting a method for function 'unique': cannot open the connection\n"
  },
  {
    "id": "ldas",
    "step": "tidy",
    "error": "Error in `dplyr::mutate()`:\nℹ In argument: `variable = varname`.\nCaused by error:\n! object 'varname' not found\n"
  },
  {
    "id": "loca_hydro",
    "step": "tidy",
    "error": "Error: [rast] file does not exist: /vsicurl/ftp://gdo-dcp.llnl.gov/dcp/archive/cmip5/loca_hydro/LOCA_VIC_dpierce_2017-02-28/ACCESS1-0/vic_output.historical.netcdf/ET.1950.v0.nc\n"
  },
  {
    "id": "MERRA2",
    "step": "pull",
    "error": "Error in h(simpleError(msg, call)): error in evaluating the argument 'y' in selecting a method for function 'merge': NetCDF: Access failure\n"
  },
  {
    "id": "modis",
    "step": "pull",
    "error": "Error in open.connection(x, \"rb\"): cannot open the connection\n"
  },
  {
    "id": "prism_daily",
    "step": "pull",
    "error": "Error in open.nc(URL): NetCDF: I/O failure\n"
  },
  {
    "id": "prism_daily",
    "step": "tidy",
    "error": "Error in `dplyr::mutate()`:\nℹ In argument: `variable = varname`.\nCaused by error:\n! object 'varname' not found\n"
  },
  {
    "id": "worldclim_hist",
    "step": "tidy",
    "error": "Error in h(simpleError(msg, call)): error in evaluating the argument 'x' in selecting a method for function 'xmin': object 'r' not found\n"
  }
]
